shadcn/__init__.py
shadcn/filters.py
shadcn/main.html
shadcn/mkdocs_theme.yml
shadcn/components/bottom_sidebar_item.html
shadcn/components/breadcrumbs.html
shadcn/components/datetime.html
shadcn/components/icon.html
shadcn/components/sidebar_item.html
shadcn/components/tag.html
shadcn/css/base.css
shadcn/css/geist.css
shadcn/css/katex.min.css
shadcn/css/pygments/a11y-dark.css
shadcn/css/pygments/a11y-high-contrast-dark.css
shadcn/css/pygments/a11y-high-contrast-light.css
shadcn/css/pygments/a11y-light.css
shadcn/css/pygments/abap.css
shadcn/css/pygments/algol.css
shadcn/css/pygments/algol_nu.css
shadcn/css/pygments/all.css
shadcn/css/pygments/arduino.css
shadcn/css/pygments/autumn.css
shadcn/css/pygments/blinds-dark.css
shadcn/css/pygments/blinds-light.css
shadcn/css/pygments/borland.css
shadcn/css/pygments/bw.css
shadcn/css/pygments/coffee.css
shadcn/css/pygments/colorful.css
shadcn/css/pygments/default.css
shadcn/css/pygments/dracula.css
shadcn/css/pygments/emacs.css
shadcn/css/pygments/friendly.css
shadcn/css/pygments/friendly_grayscale.css
shadcn/css/pygments/fruity.css
shadcn/css/pygments/github-dark-colorblind.css
shadcn/css/pygments/github-dark-high-contrast.css
shadcn/css/pygments/github-dark.css
shadcn/css/pygments/github-light-colorblind.css
shadcn/css/pygments/github-light-high-contrast.css
shadcn/css/pygments/github-light.css
shadcn/css/pygments/gotthard-dark.css
shadcn/css/pygments/gotthard-light.css
shadcn/css/pygments/greative.css
shadcn/css/pygments/gruvbox-dark.css
shadcn/css/pygments/gruvbox-light.css
shadcn/css/pygments/igor.css
shadcn/css/pygments/inkpot.css
shadcn/css/pygments/lightbulb.css
shadcn/css/pygments/lilypond.css
shadcn/css/pygments/lovelace.css
shadcn/css/pygments/manni.css
shadcn/css/pygments/material.css
shadcn/css/pygments/monokai.css
shadcn/css/pygments/murphy.css
shadcn/css/pygments/native.css
shadcn/css/pygments/nord-darker.css
shadcn/css/pygments/nord.css
shadcn/css/pygments/one-dark.css
shadcn/css/pygments/paraiso-dark.css
mkdocs_shadcn-0.9.7.dist-info/METADATA
mkdocs_shadcn-0.9.7.dist-info/WHEEL
mkdocs_shadcn-0.9.7.dist-info/entry_points.txt
mkdocs_shadcn-0.9.7.dist-info/licenses/LICENSE
mkdocs_shadcn-0.9.7.dist-info/RECORD
