Metadata-Version: 2.4
Name: mkdocs-shadcn
Version: 0.9.7
Summary: Documentation that also shines
Author-email: Alban Siffer <31479857+asiffer@users.noreply.github.com>
License-File: LICENSE
Requires-Python: >=3.8
Requires-Dist: bottle>=0.13.2
Requires-Dist: gitpython>=3.1.45
Requires-Dist: mkdocs>=1.6.1
Requires-Dist: pymdown-extensions>=10.14.3
